setup.py
pdftables/TableFinder.py
pdftables/__init__.py
pdftables/display.py
pdftables/pdftables.py
pdftables/pdftables_analysis.py
pdftables/runtables.py
pdftables/tree.py
pdftables.egg-info/PKG-INFO
pdftables.egg-info/SOURCES.txt
pdftables.egg-info/dependency_links.txt
pdftables.egg-info/entry_points.txt
pdftables.egg-info/namespace_packages.txt
pdftables.egg-info/not-zip-safe
pdftables.egg-info/requires.txt
pdftables.egg-info/top_level.txt
test/test_Table_class.py
test/test_all_sample_data.py
test/test_comb.py
test/test_contains_tables.py
test/test_finds_tables.py
test/test_get_tables.py
test/test_tree.py